<?xml version="1.0" encoding="UTF-8"?>
<!DOCTYPE mapper PUBLIC "-//mybatis.org//DTD Mapper 3.0//EN" "http://mybatis.org/dtd/mybatis-3-mapper.dtd">

<!-- user -->
<mapper namespace="com.dreamchaser.depository_manage.mapper.UserMapper">
    <!-- 字段映射 -->
    <resultMap id="userMap" type="com.dreamchaser.depository_manage.entity.User">
        <id column="id" property="id" jdbcType="INTEGER" />
        <result column="uname" property="uname" jdbcType="VARCHAR" />
        <result column="authority" property="authority" jdbcType="VARCHAR" />
        <result column="pwd" property="pwd" jdbcType="VARCHAR" />
        <result column="sex" property="sex" jdbcType="VARCHAR" />
        <result column="depository_id" property="depositoryId" jdbcType="INTEGER" />
        <result column="entry_date" property="entryDate" jdbcType="TIMESTAMP" />
        <result column="email" property="email" jdbcType="VARCHAR" />
        <result column="phone" property="phone" jdbcType="VARCHAR" />
    </resultMap>

    <!-- 表查询字段(不敏感信息) -->
    <sql id="noSensitiveColumns">
        u.id, u.uname,  u.sex, u.entry_date
    </sql>
    <!-- 表查询字段 -->
    <sql id="allColumns">
        u.id, u.uname, u.authority, u.pwd, u.sex, u.depository_id, u.entry_date, u.email, 
        u.phone
    </sql>
    <!-- This code was generated by TableGo tools, mark 2 end. -->
    <!-- 查询该表的行数 -->
    <select id="findCount" resultType="integer">
        SELECT
        count(*)
        FROM user u
    </select>
    <!-- 根据条件查询数据的数量 -->
    <select id="findCountByCondition" resultType="integer" parameterType="map">
        SELECT
        count(*)
        FROM user u WHERE 1 = 1
        <if test="uname != null and uname != ''">
            AND u.uname LIKE CONCAT('%', #{uname}, '%')
        </if>
        <if test="authority != null and authority != ''">
            AND u.authority LIKE CONCAT('%', #{authority}, '%')
        </if>
        <if test="pwd != null and pwd != ''">
            AND u.pwd LIKE CONCAT('%', #{pwd}, '%')
        </if>
        <if test="sex != null and sex != ''">
            AND u.sex LIKE CONCAT('%', #{sex}, '%')
        </if>
        <if test="depositoryId != null">
            AND u.depository_id = #{depositoryId}
        </if>
        <if test="entryDate != null">
            AND u.entry_date = #{entryDate}
        </if>
        <if test="email != null and email != ''">
            AND u.email LIKE CONCAT('%', #{email}, '%')
        </if>
        <if test="phone != null and phone != ''">
            AND u.phone LIKE CONCAT('%', #{phone}, '%')
        </if>

    </select>
    <!-- 查询所有数据 -->
    <select id="findUserAll" resultMap="userMap">
        SELECT
        <include refid="allColumns" />
        FROM user u
    </select>

    <!-- 根据id查询数据列表 -->
    <select id="findUserNameById" resultType="string" parameterType="int">
        SELECT
        u.uname
        FROM user u WHERE  u.id=#{id}
    </select>


    <!-- 根据email查询数据列表 -->
    <select id="findUserByEmail" resultMap="userMap" parameterType="string">
        SELECT
        <include refid="allColumns" />
        FROM user u WHERE  u.email LIKE CONCAT('%', #{email}, '%')
    </select>

    <!-- 根据条件参数查询数据列表 -->
    <select id="findUsersByCondition" resultMap="userMap" parameterType="map">
        SELECT
        <include refid="allColumns" />
        FROM user u WHERE 1 = 1
        <if test="uname != null and uname != ''">
            AND u.uname LIKE CONCAT('%', #{uname}, '%')
        </if>
        <if test="authority != null and authority != ''">
            AND u.authority LIKE CONCAT('%', #{authority}, '%')
        </if>
        <if test="pwd != null and pwd != ''">
            AND u.pwd LIKE CONCAT('%', #{pwd}, '%')
        </if>
        <if test="sex != null and sex != ''">
            AND u.sex LIKE CONCAT('%', #{sex}, '%')
        </if>
        <if test="depositoryId != null">
            AND u.depository_id = #{depositoryId}
        </if>
        <if test="entryDate != null">
            AND u.entry_date = #{entryDate}
        </if>
        <if test="email != null and email != ''">
            AND u.email LIKE CONCAT('%', #{email}, '%')
        </if>
        <if test="phone != null and phone != ''">
            AND u.phone LIKE CONCAT('%', #{phone}, '%')
        </if>
        <if test="begin != null and size != null">
            LIMIT #{begin},#{size}
        </if>
    </select>
    
    <!-- 根据条件参数查询数据列表 -->
    <select id="findUserByCondition" resultMap="userMap" parameterType="map">
        SELECT
        <include refid="allColumns" />
        FROM user u WHERE 1 = 1
        <if test="uname != null and uname != ''">
            AND u.uname LIKE CONCAT('%', #{uname}, '%')
        </if>
        <if test="authority != null and authority != ''">
            AND u.authority LIKE CONCAT('%', #{authority}, '%')
        </if>
        <if test="pwd != null and pwd != ''">
            AND u.pwd LIKE CONCAT('%', #{pwd}, '%')
        </if>
        <if test="sex != null and sex != ''">
            AND u.sex LIKE CONCAT('%', #{sex}, '%')
        </if>
        <if test="depositoryId != null">
            AND u.depository_id = #{depositoryId}
        </if>
        <if test="entryDate != null">
            AND u.entry_date = #{entryDate}
        </if>
        <if test="email != null and email != ''">
            AND u.email LIKE CONCAT('%', #{email}, '%')
        </if>
        <if test="phone != null and phone != ''">
            AND u.phone LIKE CONCAT('%', #{phone}, '%')
        </if>
    </select>

    <!-- 根据主键查询数据 -->
    <select id="findUserById" resultMap="userMap" parameterType="integer">
        SELECT
        <include refid="allColumns" />
        FROM user u WHERE u.id = #{id}
    </select>
    
    <!-- 根据主键查询数据 -->
    <select id="findUserByIds" resultMap="userMap" parameterType="list">
        SELECT
        <include refid="allColumns" />
        FROM user u WHERE u.id IN
        <foreach collection="list" index="index" item="id" open="(" separator="," close=")">
            #{id}
        </foreach>
    </select>
    
    <!-- 插入数据 -->
    <insert id="insertUser" parameterType="map">
        INSERT INTO user (
            id, uname, authority, pwd, sex, depository_id, entry_date, email, 
            phone
        ) VALUES (
            #{id},
            #{uname},
            #{authority},
            #{pwd},
            #{sex},
            #{depositoryId},
            #{entryDate},
            #{email},
            #{phone}
        )
    </insert>
    
    <!-- 批量插入数据 -->
    <insert id="insertUsers" parameterType="list">
        INSERT INTO user (
            id, uname, authority, pwd, sex, depository_id, entry_date, email, 
            phone
        ) VALUES
        <foreach collection="list" index="index" item="item" separator=",">
            (
                #{item.id},
                #{item.uname},
                #{item.authority},
                #{item.pwd},
                #{item.sex},
                #{item.depositoryId},
                #{item.entryDate},
                #{item.email},
                #{item.phone}
            )
        </foreach>
    </insert>
    <!-- 修改不敏感数据（这里由于并未对手机号进行验证所以这个也是非敏感信息可以给用户自己修改） -->
    <update id="updateUserNoSensitive" parameterType="map">
        UPDATE user
        <set>
            <if test='uname != null and uname!=""'>
                uname = #{uname},
            </if>
            <if test='sex != null and sex!=""'>
                sex = #{sex},
            </if>
            <if test="entryDate != null and entryDate!=''">
                entry_date = #{entryDate},
            </if>
            <if test="phone != null and phone !=''">
                phone = #{phone}
            </if>
        </set>
        WHERE id = #{id}
    </update>
    <!-- 修改数据 -->
    <update id="updateUser" parameterType="map">
        UPDATE user
        <set>
            <if test='uname != null and uname!=""'>
                uname = #{uname},
            </if>
            <if test='authority != null and authority!=""'>
                authority = #{authority},
            </if>
            <if test="pwd != null and pwd!=''">
                pwd = #{pwd},
            </if>
            <if test='sex != null and sex!=""'>
                sex = #{sex},
            </if>
            <if test="depositoryId != null and depository!=''">
                depository_id = #{depositoryId},
            </if>
            <if test="entryDate != null and entryDate!=''">
                entry_date = #{entryDate},
            </if>
            <if test="email != null and email != ''">
                email = #{email},
            </if>
            <if test="phone != null and phone !=''">
                phone = #{phone}
            </if>
        </set>
        WHERE id = #{id}
    </update>
    
    <!-- 批量修改数据 -->
    <update id="updateUsers" parameterType="list">
        <foreach collection="list" index="index" item="item" separator=";">
            UPDATE user
            <set>
                <if test="item.uname != null">
                    uname = #{item.uname},
                </if>
                <if test="item.authority != null">
                    authority = #{item.authority},
                </if>
                <if test="item.pwd != null">
                    pwd = #{item.pwd},
                </if>
                <if test="item.sex != null">
                    sex = #{item.sex},
                </if>
                <if test="item.depositoryId != null">
                    depository_id = #{item.depositoryId},
                </if>
                <if test="item.entryDate != null">
                    entry_date = #{item.entryDate},
                </if>
                <if test="item.email != null">
                    email = #{item.email},
                </if>
                <if test="item.phone != null">
                    phone = #{item.phone}
                </if>
            </set>
            WHERE id = #{item.id}
        </foreach>
    </update>
    
    <!-- 根据主键删除数据 -->
    <delete id="deleteUserById" parameterType="integer">
        DELETE FROM user WHERE id = #{id}
    </delete>
    
    <!-- 根据主键批量删除数据 -->
    <delete id="deleteUserByIds" parameterType="list">
        DELETE FROM user WHERE id IN
        <!-- 单参数时，List对象只能为list，数组对象只能为array，多参数用map时，collection参数才为KeyName -->
        <foreach collection="list" index="index" item="id" open="(" separator="," close=")">
            #{id}
        </foreach>
    </delete>
</mapper>